LICENSE
README.md
setup.py
examples/__init__.py
py2be/__init__.py
py2be/truthy.py
py2be.egg-info/PKG-INFO
py2be.egg-info/SOURCES.txt
py2be.egg-info/dependency_links.txt
py2be.egg-info/top_level.txt
py2be/internal/__init__.py
tests/test_truthy.py