Metadata-Version: 2.1
Name: py2be
Version: 0.0.1
Summary: Simple Python library determining whether strings indicate truey or falsy values
Home-page: https://github.com/synesissoftware/diagnosticism.Python
Author: Matt Wilson
Author-email: matthew@synesis.com.au
License: BSD-3-Clause
Keywords: configuration environment string traits
Platform: UNKNOWN
Classifier: Intended Audience :: Developers
Classifier: License :: OSI Approved :: BSD License
Classifier: Natural Language :: English
Classifier: Operating System :: OS Independent
Classifier: Programming Language :: Python
Classifier: Programming Language :: Python :: 2
Classifier: Programming Language :: Python :: 3
License-File: LICENSE
